COPYING
COPYING.LESSER
MANIFEST.in
README.txt
setup.py
non-waferslim/import_me.py
non-waferslim/import_twisted.py
non-waferslim/module_with_state.py
waferslim/__init__.py
waferslim/converters.py
waferslim/execution.py
waferslim/fixtures.py
waferslim/instructions.py
waferslim/logging.conf
waferslim/protocol.py
waferslim/server.py
waferslim.egg-info/PKG-INFO
waferslim.egg-info/SOURCES.txt
waferslim.egg-info/dependency_links.txt
waferslim.egg-info/requires.txt
waferslim.egg-info/top_level.txt
waferslim/examples/__init__.py
waferslim/examples/decision_table.py
waferslim/examples/exception_handling.py
waferslim/examples/hash_conversion.py
waferslim/examples/helper_fixtures.py
waferslim/examples/iterable_conversion.py
waferslim/examples/library.py
waferslim/examples/method_names.py
waferslim/examples/query_table.py
waferslim/examples/script_table.py
waferslim/examples/system_under_test.py
waferslim/examples/table_table.py
waferslim/examples/values_and_symbols.py
waferslim/specs/__init__.py
waferslim/specs/converter_spec.py
waferslim/specs/execution_spec.py
waferslim/specs/fixtures_spec.py
waferslim/specs/instruction_spec.py
waferslim/specs/integration.py
waferslim/specs/protocol_spec.py
waferslim/specs/spec_classes.py