Metadata-Version: 1.1
Name: waferslim
Version: 1.0.2
Summary: A python port of the fitnesse slim server and protocols
Home-page: http://withaherring.blogspot.com/
Author: tim bacon
Author-email: timbacon at gmail dotcom
License: GNU Lesser General Public License v3 (LGPL v3)
Platform: Windows
Platform: Linux
Platform: Solaris
Platform: Mac OS-X
Platform: Unix
Classifier: Development Status :: 5 - Production/Stable
Classifier: Environment :: Console
Classifier: Intended Audience :: Developers
Classifier: License :: OSI Approved :: GNU Library or Lesser General Public License (LGPL)
Classifier: Natural Language :: English
Classifier: Operating System :: OS Independent
Classifier: Programming Language :: Python :: 2.6
Classifier: Topic :: Software Development :: Build Tools
Classifier: Topic :: Software Development :: Documentation
Classifier: Topic :: Software Development :: Libraries :: Python Modules
Classifier: Topic :: Software Development :: Quality Assurance
Classifier: Topic :: Software Development :: Testing
Classifier: Topic :: Utilities
Requires: lancelot
Provides: waferslim
